LICENSE
MANIFEST.in
README.rst
alpinosample.export
proper.prm
sample.prm
setup.py
bin/discodop
disco_dop.egg-info/PKG-INFO
disco_dop.egg-info/SOURCES.txt
disco_dop.egg-info/dependency_links.txt
disco_dop.egg-info/entry_points.txt
disco_dop.egg-info/requires.txt
disco_dop.egg-info/top_level.txt
discodop/__init__.py
discodop/_fragments.c
discodop/bit.c
discodop/bitcount.h
discodop/cli.py
discodop/coarsetofine.c
discodop/containers.c
discodop/demos.py
discodop/disambiguation.c
discodop/estimates.c
discodop/eval.py
discodop/fragments.py
discodop/functiontags.py
discodop/gen.py
discodop/grammar.py
discodop/heads.py
discodop/kbest.c
discodop/lexicon.py
discodop/macros.h
discodop/parser.py
discodop/pcfg.c
discodop/plcfrs.c
discodop/punctuation.py
discodop/runexp.py
discodop/tree.py
discodop/treebank.py
discodop/treebanktransforms.py
discodop/treedist.py
discodop/treesearch.py
discodop/treetransforms.py
discodop/util.py
web/browse.py
web/parse.py
web/treedraw.py
web/treesearch.py
web/corpus/12.HAMILTON.mrg
web/corpus/13.HAMILTON.mrg
web/corpus/27.HAMILTON.mrg
web/static/fragmacros.txt
web/static/main.js
web/static/parse.ico
web/static/regexmacros.txt
web/static/style.css
web/static/tgrepmacros.txt
web/static/treesearch.ico
web/static/xpathmacros.txt
web/templates/browse.html
web/templates/browsemain.html
web/templates/browsesents.html
web/templates/draw.html
web/templates/parse.html
web/templates/parsetree.html
web/templates/search.html
web/templates/searchresults.html