Metadata-Version: 1.1
Name: disco-dop
Version: 0.5.2
Summary: Discontinuous Data-Oriented Parsing
Home-page: http://discodop.readthedocs.io
Author: Andreas van Cranenburgh
Author-email: A.W.vanCranenburgh@uva.nl
License: UNKNOWN
Platform: UNKNOWN
Classifier: Development Status :: 4 - Beta
Classifier: Environment :: Console
Classifier: Environment :: Web Environment
Classifier: Intended Audience :: Science/Research
Classifier: License :: OSI Approved :: GNU General Public License (GPL)
Classifier: Operating System :: POSIX
Classifier: Programming Language :: Python :: 2.7
Classifier: Programming Language :: Python :: 3.3
Classifier: Programming Language :: Cython
Classifier: Topic :: Text Processing :: Linguistic
Requires: numpy
Requires: roaringbitmap
Requires: pytest
Requires: sphinx
Requires: cython
